{
  "_class": "rectangle",
  "booleanOperation": -1,
  "clippingMaskMode": 0,
  "do_objectID": "12E83E74-8FCA-44E3-B854-B71E0011122F",
  "edited": true,
  "exportOptions": {
    "_class": "exportOptions",
    "do_objectID": "51470635-2C50-4340-98CB-0E8113C22399",
    "exportFormats": [
    ],
    "includedLayerIds": [
    ],
    "layerOptions": 0,
    "shouldTrim": false
  },
  "fixedRadius": 0,
  "frame": {
    "_class": "rect",
    "constrainProportions": false,
    "do_objectID": "303E37ED-DEDC-4344-ABB7-C2C17884E4F4",
    "height": 38.86638029274715,
    "width": 37.46263142446809,
    "x": -2.790093032417569,
    "y": -1.540610438614272
  },
  "hasClippingMask": false,
  "hasConvertedToNewRoundCorners": true,
  "isClosed": true,
  "isFixedToViewport": false,
  "isFlippedHorizontal": false,
  "isFlippedVertical": false,
  "isLocked": false,
  "isVisible": true,
  "layerListExpandedType": 0,
  "name": "Rectangle 9",
  "nameIsFixed": false,
  "pointRadiusBehaviour": 1,
  "points": [
    {
      "_class": "curvePoint",
      "cornerRadius": 0,
      "curveFrom": "{0, 0.90012345206423339}",
      "curveMode": 1,
      "curveTo": "{0, 0.90012345206423339}",
      "hasCurveFrom": false,
      "hasCurveTo": false,
      "point": "{0, 0.90012345206423339}"
    },
    {
      "_class": "curvePoint",
      "cornerRadius": 0,
      "curveFrom": "{0.93122604888304039, 0}",
      "curveMode": 1,
      "curveTo": "{0.93122604888304039, 0}",
      "hasCurveFrom": false,
      "hasCurveTo": false,
      "point": "{0.93122604888304039, 0}"
    },
    {
      "_class": "curvePoint",
      "cornerRadius": 0,
      "curveFrom": "{1, 0.056787949547342703}",
      "curveMode": 1,
      "curveTo": "{1, 0.056787949547342703}",
      "hasCurveFrom": false,
      "hasCurveTo": false,
      "point": "{1, 0.056787949547342703}"
    },
    {
      "_class": "curvePoint",
      "cornerRadius": 0,
      "curveFrom": "{0.021081121346810301, 1}",
      "curveMode": 1,
      "curveTo": "{0.021081121346810301, 1}",
      "hasCurveFrom": false,
      "hasCurveTo": false,
      "point": "{0.021081121346810301, 1}"
    }
  ],
  "resizingConstraint": 63,
  "resizingType": 0,
  "rotation": 0,
  "shouldBreakMaskChain": false,
  "style": {
    "_class": "style",
    "blur": {
      "_class": "blur",
      "center": "{0.5, 0.5}",
      "do_objectID": "BC843C8D-51BB-4562-97A6-B2312A913FA5",
      "isEnabled": false,
      "motionAngle": 0,
      "radius": 6.666666666666667,
      "saturation": 1,
      "type": 0
    },
    "do_objectID": "38DFF6F5-55A8-42EC-91AE-959B2B05BBB4",
    "endMarkerType": 0,
    "fills": [
      {
        "_class": "fill",
        "color": {
          "_class": "color",
          "alpha": 1,
          "blue": 0,
          "green": 0,
          "red": 0
        },
        "fillType": 0,
        "isEnabled": true,
        "noiseIndex": 0,
        "noiseIntensity": 0,
        "patternFillType": 1,
        "patternTileScale": 1
      }
    ],
    "miterLimit": 10,
    "startMarkerType": 0,
    "windingRule": 1
  }
}