{
  "_class": "bitmap",
  "booleanOperation": 0,
  "clippingMask": "{{0, 0}, {1, 1}}",
  "clippingMaskMode": 0,
  "do_objectID": "88E61F07-A525-4FBD-B311-CF52A05A3850",
  "exportOptions": {
    "_class": "exportOptions",
    "do_objectID": "69ACCF84-AD02-49E1-9FD4-CEDBFE0B82C8",
    "exportFormats": [
    ],
    "includedLayerIds": [
    ],
    "layerOptions": 0,
    "shouldTrim": false
  },
  "fillReplacesImage": false,
  "frame": {
    "_class": "rect",
    "constrainProportions": true,
    "do_objectID": "C85B87DE-1C23-4781-854F-D0DB63ED250C",
    "height": 460,
    "width": 654.5,
    "x": -0.25,
    "y": -0.25
  },
  "hasClippingMask": false,
  "image": {
    "_class": "MSJSONFileReference",
    "_ref": "images/0d2b48a192dbbc9047ca20eb51647f522f1d9cc5.png",
    "_ref_class": "MSImageData"
  },
  "intendedDPI": 0,
  "isFixedToViewport": false,
  "isFlippedHorizontal": false,
  "isFlippedVertical": false,
  "isLocked": false,
  "isVisible": true,
  "layerListExpandedType": 0,
  "name": "Multiply",
  "nameIsFixed": true,
  "resizingConstraint": 63,
  "resizingType": 0,
  "rotation": 0,
  "shouldBreakMaskChain": false,
  "style": {
    "_class": "style",
    "blur": {
      "_class": "blur",
      "center": "{0.5, 0.5}",
      "do_objectID": "8ECEDDB8-C73F-4D51-94BD-9C81B4930C5E",
      "isEnabled": false,
      "motionAngle": 0,
      "radius": 2.5,
      "saturation": 1,
      "type": 0
    },
    "contextSettings": {
      "_class": "graphicsContextSettings",
      "blendMode": 2,
      "do_objectID": "B4FC464E-CECA-4153-AA56-2105A8D0B460",
      "opacity": 0.8610657649253731
    },
    "do_objectID": "8C38F1C1-DABB-4383-B6A1-5E0C02FEAFD3",
    "endMarkerType": 0,
    "miterLimit": 10,
    "startMarkerType": 0,
    "windingRule": 1
  }
}