{
  "_class": "bitmap",
  "booleanOperation": 0,
  "clippingMask": "{{0, 0}, {1, 1}}",
  "clippingMaskMode": 0,
  "do_objectID": "D525D1CE-79F9-415B-A668-A38F19B48243",
  "exportOptions": {
    "_class": "exportOptions",
    "do_objectID": "5BE29808-4B2F-481A-AF43-2AB1A832157D",
    "exportFormats": [
    ],
    "includedLayerIds": [
    ],
    "layerOptions": 0,
    "shouldTrim": false
  },
  "fillReplacesImage": false,
  "frame": {
    "_class": "rect",
    "constrainProportions": true,
    "do_objectID": "AD044829-5668-4B8E-9EF0-2959B6F71909",
    "height": 460,
    "width": 654.5,
    "x": -0.5,
    "y": -0.25
  },
  "hasClippingMask": false,
  "image": {
    "_class": "MSJSONFileReference",
    "_ref": "images/fc8df760e302f9c627fd89c620d3977ad688c083.png",
    "_ref_class": "MSImageData"
  },
  "intendedDPI": 0,
  "isFixedToViewport": false,
  "isFlippedHorizontal": false,
  "isFlippedVertical": false,
  "isLocked": false,
  "isVisible": true,
  "layerListExpandedType": 0,
  "name": "Overlay",
  "nameIsFixed": true,
  "resizingConstraint": 63,
  "resizingType": 0,
  "rotation": 0,
  "shouldBreakMaskChain": false,
  "style": {
    "_class": "style",
    "blur": {
      "_class": "blur",
      "center": "{0.5, 0.5}",
      "do_objectID": "DF3CBBF3-A633-4307-9891-4737AEE0779D",
      "isEnabled": false,
      "motionAngle": 0,
      "radius": 2.5,
      "saturation": 1,
      "type": 0
    },
    "contextSettings": {
      "_class": "graphicsContextSettings",
      "blendMode": 7,
      "do_objectID": "BC94B724-8040-4BC3-838F-3B4A48F5A158",
      "opacity": 1
    },
    "do_objectID": "94A7AA72-618B-492B-B079-7CC501BBA1C2",
    "endMarkerType": 0,
    "miterLimit": 10,
    "startMarkerType": 0,
    "windingRule": 1
  }
}